lswifi/__init__.py
lswifi/__main__.py
lswifi/__version__.py
lswifi/app.py
lswifi/appsetup.py
lswifi/client.py
lswifi/completions.py
lswifi/constants.py
lswifi/elements.py
lswifi/guid.py
lswifi/helpers.py
lswifi/pcap.py
lswifi/slog.py
lswifi/wlanapi.py
lswifi/schemas/__init__.py
lswifi/schemas/auth.py
lswifi/schemas/band.py
lswifi/schemas/beacon.py
lswifi/schemas/bssid.py
lswifi/schemas/capabilities.py
lswifi/schemas/channel.py
lswifi/schemas/encryption.py
lswifi/schemas/ie.py
lswifi/schemas/modes.py
lswifi/schemas/out.py
lswifi/schemas/phy.py
lswifi/schemas/pmf.py
lswifi/schemas/rates.py
lswifi/schemas/rnr.py
lswifi/schemas/security.py
lswifi/schemas/signalquality.py
lswifi-0.1.62.dist-info/licenses/AUTHORS.md
lswifi-0.1.62.dist-info/licenses/LICENSE
lswifi-0.1.62.dist-info/METADATA
lswifi-0.1.62.dist-info/WHEEL
lswifi-0.1.62.dist-info/entry_points.txt
lswifi-0.1.62.dist-info/top_level.txt
lswifi-0.1.62.dist-info/RECORD
