Metadata-Version: 2.4
Name: lswifi
Version: 0.1.62
Summary: a CLI-centric Wi-Fi scanning tool for Windows
Home-page: https://github.com/joshschmelzle/lswifi
Author: Josh Schmelzle
Author-email: josh@joshschmelzle.com
License: BSD-3-Clause
Keywords: lswifi,scanner,wireless,wifi,802.11,wlan,rlan,native wifi,wlanapi
Platform: win32
Classifier: Natural Language :: English
Classifier: Development Status :: 3 - Alpha
Classifier: Environment :: Console
Classifier: License :: OSI Approved :: BSD License
Classifier: Programming Language :: Python :: 3 :: Only
Classifier: Programming Language :: Python :: 3.9
Classifier: Programming Language :: Python :: 3.10
Classifier: Programming Language :: Python :: 3.11
Classifier: Programming Language :: Python :: 3.12
Classifier: Programming Language :: Python :: 3.13
Classifier: Intended Audience :: Information Technology
Classifier: Intended Audience :: System Administrators
Classifier: Intended Audience :: Telecommunications Industry
Classifier: Topic :: Utilities
Classifier: Topic :: System :: Networking
Classifier: Topic :: System :: Networking :: Monitoring
Classifier: Environment :: Win32 (MS Windows)
Classifier: Operating System :: Microsoft :: Windows :: Windows 10
Classifier: Operating System :: Microsoft :: Windows :: Windows 11
Requires-Python: >=3.9
License-File: LICENSE
License-File: AUTHORS.md
Provides-Extra: dev
Requires-Dist: altgraph==0.17.4; extra == "dev"
Requires-Dist: astor==0.8.1; extra == "dev"
Requires-Dist: attrs==25.3.0; extra == "dev"
Requires-Dist: autoflake==2.3.1; extra == "dev"
Requires-Dist: black==25.1.0; extra == "dev"
Requires-Dist: build==1.2.2.post1; extra == "dev"
Requires-Dist: cachetools==5.5.2; extra == "dev"
Requires-Dist: certifi==2026.1.4; extra == "dev"
Requires-Dist: cfgv==3.4.0; extra == "dev"
Requires-Dist: chardet==5.2.0; extra == "dev"
Requires-Dist: charset-normalizer==3.4.4; extra == "dev"
Requires-Dist: click==8.1.8; extra == "dev"
Requires-Dist: colorama==0.4.6; extra == "dev"
Requires-Dist: coverage==7.8.0; extra == "dev"
Requires-Dist: defusedxml==0.7.1; extra == "dev"
Requires-Dist: distlib==0.3.9; extra == "dev"
Requires-Dist: filelock==3.20.3; extra == "dev"
Requires-Dist: flake8==7.2.0; extra == "dev"
Requires-Dist: flake8-alfred==1.1.1; extra == "dev"
Requires-Dist: flake8-blind-except==0.2.1; extra == "dev"
Requires-Dist: flake8-bugbear==24.12.12; extra == "dev"
Requires-Dist: flake8-builtins==2.5.0; extra == "dev"
Requires-Dist: flake8-fixme==1.1.1; extra == "dev"
Requires-Dist: flake8-logging-format==2024.24.12; extra == "dev"
Requires-Dist: flake8-requirements==2.2.1; extra == "dev"
Requires-Dist: flake8-simplify==0.21.0; extra == "dev"
Requires-Dist: flake8-string-format==0.3.0; extra == "dev"
Requires-Dist: flake8-variables-names==0.0.6; extra == "dev"
Requires-Dist: genbadge[coverage]==1.1.3; extra == "dev"
Requires-Dist: identify==2.6.10; extra == "dev"
Requires-Dist: idna==3.11; extra == "dev"
Requires-Dist: iniconfig==2.1.0; extra == "dev"
Requires-Dist: isort==6.0.1; extra == "dev"
Requires-Dist: mccabe==0.7.0; extra == "dev"
Requires-Dist: mock==5.2.0; extra == "dev"
Requires-Dist: mypy==1.15.0; extra == "dev"
Requires-Dist: mypy-extensions==1.1.0; extra == "dev"
Requires-Dist: nodeenv==1.9.1; extra == "dev"
Requires-Dist: packaging==25.0; extra == "dev"
Requires-Dist: pathspec==0.12.1; extra == "dev"
Requires-Dist: pillow==12.1.0; extra == "dev"
Requires-Dist: pip-tools==7.4.1; extra == "dev"
Requires-Dist: platformdirs==4.3.8; extra == "dev"
Requires-Dist: pluggy==1.5.0; extra == "dev"
Requires-Dist: pre-commit==4.2.0; extra == "dev"
Requires-Dist: pycodestyle==2.13.0; extra == "dev"
Requires-Dist: pyflakes==3.3.2; extra == "dev"
Requires-Dist: pyinstaller==6.13.0; extra == "dev"
Requires-Dist: pyinstaller-hooks-contrib==2025.4; extra == "dev"
Requires-Dist: pyproject-api==1.9.0; extra == "dev"
Requires-Dist: pyproject-hooks==1.2.0; extra == "dev"
Requires-Dist: pytest==8.3.5; extra == "dev"
Requires-Dist: pyyaml==6.0.2; extra == "dev"
Requires-Dist: requests==2.32.5; extra == "dev"
Requires-Dist: scapy==2.6.1; extra == "dev"
Requires-Dist: tox==4.25.0; extra == "dev"
Requires-Dist: typing-extensions==4.13.2; extra == "dev"
Requires-Dist: urllib3==2.6.3; extra == "dev"
Requires-Dist: virtualenv==20.36.1; extra == "dev"
Requires-Dist: wheel==0.45.1; extra == "dev"
Dynamic: author
Dynamic: author-email
Dynamic: classifier
Dynamic: description
Dynamic: description-content-type
Dynamic: home-page
Dynamic: keywords
Dynamic: license
Dynamic: license-file
Dynamic: platform
Dynamic: provides-extra
Dynamic: requires-python
Dynamic: summary
